honk.py
honk-0.5.dist-info/DESCRIPTION.rst
honk-0.5.dist-info/METADATA
honk-0.5.dist-info/RECORD
honk-0.5.dist-info/WHEEL
honk-0.5.dist-info/entry_points.txt
honk-0.5.dist-info/metadata.json
honk-0.5.dist-info/top_level.txt
