Metadata-Version: 2.0
Name: honk
Version: 0.5
Summary: Tool for dumping output of HTTP requests
Home-page: https://github.com/ryantownshend/honk
Author: Ryan Townshend
Author-email: citizen.townshend@gmail.com
License: UNKNOWN
Platform: UNKNOWN
Requires-Dist: PyYAML (>=3.12)
Requires-Dist: click (>=6.7)
Requires-Dist: click-log (>=0.2.1)
Requires-Dist: tabulate (>=0.8.2)
